auto_ml/__init__.py
auto_ml/__version__.py
auto_ml/automl.py
auto_ml/default_algorithms.yml
auto_ml/default_processor.yml
auto_ml/estimator.py
auto_ml/hyper_config.py
auto_ml/search_hypers.yml
auto_ml/base/__init__.py
auto_ml/base/classifier_algorithms.py
auto_ml/base/model_selection.py
auto_ml/base/regressor_algorithms.py
auto_ml/ensemble/__init__.py
auto_ml/ensemble/model_ensemble.py
auto_ml/metrics/__init__.py
auto_ml/metrics/scorer.py
auto_ml/neural_networks/__init__.py
auto_ml/neural_networks/basic_cnn_net.py
auto_ml/neural_networks/basic_net.py
auto_ml/neural_networks/dnn_net.py
auto_ml/neural_networks/neural_network_search.py
auto_ml/neural_networks/residual_net.py
auto_ml/neural_networks/rnn_net.py
auto_ml/neural_networks/wide_deep_net.py
auto_ml/pipelines/__init__.py
auto_ml/pipelines/pipeline_training.py
auto_ml/preprocessing/__init__.py
auto_ml/preprocessing/feature_selection.py
auto_ml/preprocessing/imputation.py
auto_ml/preprocessing/minmax.py
auto_ml/preprocessing/norlization.py
auto_ml/preprocessing/onehotencoding.py
auto_ml/preprocessing/pca_reduction.py
auto_ml/preprocessing/processing_base.py
auto_ml/preprocessing/processing_factory.py
auto_ml/preprocessing/standardization.py
auto_ml/test/__init__.py
auto_ml/test/get_test_data.py
auto_ml/test/test_auto_ml.py
auto_ml/utils/CONSTANT.py
auto_ml/utils/__init__.py
auto_ml/utils/backend_obj.py
auto_ml/utils/data_rela.py
auto_ml/utils/func_utils.py
auto_ml/utils/logger.py
auto_ml/utils/params_config.py
auto_ml/utils/paths.py
auto_ml_cl-0.0.21.dist-info/METADATA
auto_ml_cl-0.0.21.dist-info/WHEEL
auto_ml_cl-0.0.21.dist-info/top_level.txt
auto_ml_cl-0.0.21.dist-info/RECORD
